{"scanned_at":"2026-07-01T22:45:28Z","universe":"all","threshold":65,"count":21,"market":{"regime":"risk_on","benchmarks":{"SPY":{"price":745.76,"chg_1d":-0.0014,"chg_5d":0.0171,"chg_1m":-0.0168,"trend":"uptrend","rsi14":54.2,"label":"S&P 500"},"QQQ":{"price":725.17,"chg_1d":-0.0152,"chg_5d":0.0205,"chg_1m":-0.0237,"trend":"uptrend","rsi14":52.4,"label":"Nasdaq 100"},"^AXJO":{"price":8778.7,"chg_1d":-0.0051,"chg_5d":-0.0009,"chg_1m":0.0054,"trend":"mixed","rsi14":50.7,"label":"ASX 200"},"BTC-USD":{"price":60403.5,"chg_1d":0.0315,"chg_5d":0.0064,"chg_1m":-0.017,"trend":"downtrend","rsi14":39.0,"label":"Bitcoin"}},"breadth":{"pct_above_50dma":0.5,"symbols":102,"pct_above_200dma":0.48,"pct_rsi_bullish":0.48}},"suggestions":[{"symbol":"VRTX","market":"US","price":498.010009765625,"chg_1d":0.0026,"conviction":94,"tier":"both","reasons":["Uptrend (above rising 50/200-day MAs)","Volume accumulation (OBV rising ahead of price)","Fresh golden cross (50-day over 200-day)","Holding near 52-week highs","ROE 24%","low debt/equity 0.1","strong margin 36%"],"technical":{"score":0.8791058570281384,"patterns":["uptrend","obv_accumulation","golden_cross","high_52w_momentum"],"strengths":{"uptrend":1.0,"golden_cross":0.8667,"obv_accumulation":1.0,"high_52w_momentum":0.6955},"detail":{"setup":1.0,"trend":0.8188,"momentum":0.58,"volume":1.0}},"fundamental":{"score":0.7244782857142857,"quality":1.0,"value":0.3723914285714286,"moat":1.0,"management":0.0},"snapshot":{"rsi14":73.5,"macd_hist":0.00943,"adx14":29.0,"stoch_k":91.7,"atr_pct":0.0245,"sma50_dist":0.1189,"sma200_dist":0.1237,"high_52w_dist":-0.0033,"low_52w_dist":0.3587,"vol_ratio":0.65,"ret_1m":0.136,"ret_3m":0.1153,"ret_6m":0.0831,"rel_1m":0.1528,"rel_3m":-0.0314},"trade_plan":{"entry":498.01,"stop":473.57,"target1":522.45,"target2":546.9,"rr":1.0,"atr_pct":0.0245,"method":"2x/4x ATR"},"summary":"VRTX surfaced because it lines up on two fronts at once: the chart shows a constructive setup, and the underlying business screens as high quality. The specific triggers were uptrend (above rising 50/200-day mas), volume accumulation (obv rising ahead of price), fresh golden cross (50-day over 200-day), holding near 52-week highs, roe 24%, low debt/equity 0.1, and strong margin 36%. That gives it a conviction score of 94/100 \u2014 a research lead to investigate, not a recommendation to buy.","company":{"name":"Vertex Pharmaceuticals Incorporated","sector":"Healthcare","industry":"Biotechnology","country":"United States","website":"https://www.vrtx.com","employees":6400,"held_institutions":0.97973,"held_insiders":0.00201,"description":"Vertex Pharmaceuticals Incorporated operates as a biotechnology company in the United States, Europe, and internationally.","holders":[{"name":"Capital World Investors","pct":0.1},{"name":"Blackrock Inc.","pct":0.094399996},{"name":"Capital Research Global Investors","pct":0.0832},{"name":"Vanguard Capital Management LLC","pct":0.0651},{"name":"State Street Corporation","pct":0.0462}],"backing_score":85,"strength_score":87}},{"symbol":"JPM","market":"US","price":334.07000732421875,"chg_1d":0.0206,"conviction":93,"tier":"both","reasons":["Uptrend (above rising 50/200-day MAs)","Volume accumulation (OBV rising ahead of price)","Holding near 52-week highs","strong margin 34%","reasonable P/E 16"],"technical":{"score":0.8393103322816307,"patterns":["uptrend","obv_accumulation","high_52w_momentum"],"strengths":{"uptrend":1.0,"obv_accumulation":1.0,"high_52w_momentum":0.7143},"detail":{"setup":0.8643,"trend":0.7549,"momentum":1.0,"volume":0.6803}},"fundamental":{"score":0.7374757594642857,"quality":0.8821667,"value":0.8571599285714286,"moat":0.852708375,"management":0.0},"snapshot":{"rsi14":63.3,"macd_hist":0.00082,"adx14":28.3,"stoch_k":61.9,"atr_pct":0.022,"sma50_dist":0.0701,"sma200_dist":0.0834,"high_52w_dist":-0.0031,"low_52w_dist":0.1814,"vol_ratio":0.52,"ret_1m":0.1264,"ret_3m":0.1357,"ret_6m":0.0319,"rel_1m":0.1432,"rel_3m":-0.011},"trade_plan":{"entry":334.07,"stop":319.35,"target1":348.79,"target2":363.51,"rr":1.0,"atr_pct":0.022,"method":"2x/4x ATR"},"earnings":{"date":"2026-07-14","days":13},"summary":"JPM surfaced because it lines up on two fronts at once: the chart shows a constructive setup, and the underlying business screens as high quality. The specific triggers were uptrend (above rising 50/200-day mas), volume accumulation (obv rising ahead of price), holding near 52-week highs, strong margin 34%, and reasonable p/e 16. That gives it a conviction score of 93/100 \u2014 a research lead to investigate, not a recommendation to buy.","company":{"name":"JPMorgan Chase & Co.","sector":"Financial Services","industry":"Banks - Diversified","country":"United States","website":"https://www.jpmorganchase.com","employees":320079,"held_institutions":0.7562,"held_insiders":0.0038,"description":"JPMorgan Chase & Co. operates as a bank and financial holding company in the United States, rest of North America, Europe, the Middle East, Africa, the Asia Pacific, Latin America, and the Caribbean.","holders":[{"name":"Blackrock Inc.","pct":0.0777},{"name":"Vanguard Capital Management LLC","pct":0.0617},{"name":"State Street Corporation","pct":0.0464},{"name":"Morgan Stanley","pct":0.0256},{"name":"Vanguard Portfolio Management LLC","pct":0.024500001}],"backing_score":86,"strength_score":87}},{"symbol":"QBE.AX","market":"ASX","price":24.950000762939453,"chg_1d":-0.0095,"conviction":91,"tier":"both","reasons":["Uptrend (above rising 50/200-day MAs)","Volume accumulation (OBV rising ahead of price)","Holding near 52-week highs","low debt/equity 0.3","reasonable P/E 12"],"technical":{"score":0.8011367606663728,"patterns":["uptrend","obv_accumulation","high_52w_momentum"],"strengths":{"uptrend":1.0,"obv_accumulation":1.0,"high_52w_momentum":0.7137},"detail":{"setup":0.8137,"trend":0.7825,"momentum":0.86,"volume":0.7045}},"fundamental":{"score":0.7309575814695108,"quality":0.8774906862745098,"value":0.9960124642857142,"moat":0.7230352564102562,"management":0.0},"snapshot":{"rsi14":67.0,"macd_hist":0.00396,"adx14":29.9,"stoch_k":90.2,"atr_pct":0.0175,"sma50_dist":0.0759,"sma200_dist":0.1819,"high_52w_dist":-0.0095,"low_52w_dist":0.325,"vol_ratio":0.9,"ret_1m":0.1148,"ret_3m":0.1752,"ret_6m":0.2576,"rel_1m":null,"rel_3m":null},"trade_plan":{"entry":24.95,"stop":24.08,"target1":25.82,"target2":26.7,"rr":1.0,"atr_pct":0.0175,"method":"2x/4x ATR"},"summary":"QBE.AX surfaced because it lines up on two fronts at once: the chart shows a constructive setup, and the underlying business screens as high quality. The specific triggers were uptrend (above rising 50/200-day mas), volume accumulation (obv rising ahead of price), holding near 52-week highs, low debt/equity 0.3, and reasonable p/e 12. That gives it a conviction score of 91/100 \u2014 a research lead to investigate, not a recommendation to buy.","company":{"name":"QBE Insurance Group Limited","sector":"Financial Services","industry":"Insurance - Property & Casualty","country":"Australia","website":"https://www.qbe.com","employees":13196,"held_institutions":0.57677,"held_insiders":0.00078,"description":"QBE Insurance Group Limited engages in underwriting general insurance and reinsurance risks in the Australia Pacific, North America, and internationally.","holders":[{"name":"Pacer Advisors, Inc.","pct":0.0}],"backing_score":70,"strength_score":85}},{"symbol":"BKNG","market":"US","price":182.63999938964844,"chg_1d":0.0247,"conviction":89,"tier":"both","reasons":["Volume accumulation (OBV rising ahead of price)","Double bottom recovering","strong margin 22%"],"technical":{"score":0.730730491043799,"patterns":["obv_accumulation","double_bottom"],"strengths":{"double_bottom":0.7908,"obv_accumulation":1.0},"detail":{"setup":0.8908,"trend":0.2803,"momentum":0.9739,"volume":0.7042}},"fundamental":{"score":0.7636072285714286,"quality":1.0,"value":0.5680361428571429,"moat":1.0,"management":0.0},"snapshot":{"rsi14":61.5,"macd_hist":0.00742,"adx14":16.6,"stoch_k":81.0,"atr_pct":0.036,"sma50_dist":0.0832,"sma200_dist":-0.0335,"high_52w_dist":-0.2149,"low_52w_dist":0.185,"vol_ratio":0.74,"ret_1m":0.0791,"ret_3m":0.0845,"ret_6m":-0.1609,"rel_1m":0.0959,"rel_3m":-0.0622},"trade_plan":{"entry":182.64,"stop":169.51,"target1":195.77,"target2":208.91,"rr":1.0,"atr_pct":0.036,"method":"2x/4x ATR"},"summary":"BKNG surfaced because it lines up on two fronts at once: the chart shows a constructive setup, and the underlying business screens as high quality. The specific triggers were volume accumulation (obv rising ahead of price), double bottom recovering, and strong margin 22%. That gives it a conviction score of 89/100 \u2014 a research lead to investigate, not a recommendation to buy.","company":{"name":"Booking Holdings Inc.","sector":"Consumer Cyclical","industry":"Travel Services","country":"United States","website":"https://www.bookingholdings.com","employees":24900,"held_institutions":0.97023004,"held_insiders":0.00177,"description":"Booking Holdings Inc., together with its subsidiaries, provides online and traditional travel and restaurant reservations and related services in the United States, the Netherlands, the United Kingdom, and internationally.","holders":[{"name":"Blackrock Inc.","pct":0.0856},{"name":"Vanguard Capital Management LLC","pct":0.067},{"name":"State Street Corporation","pct":0.0458},{"name":"Price (T.Rowe) Associates Inc","pct":0.0374},{"name":"JPMORGAN CHASE & CO","pct":0.0345}],"backing_score":85,"strength_score":91}},{"symbol":"ABNB","market":"US","price":147.30999755859375,"chg_1d":0.0294,"conviction":82,"tier":"both","reasons":["Uptrend (above rising 50/200-day MAs)","Holding near 52-week highs","ROE 32%","low debt/equity 0.3","strong margin 20%"],"technical":{"score":0.7470755770260096,"patterns":["uptrend","high_52w_momentum"],"strengths":{"uptrend":1.0,"high_52w_momentum":0.7382},"detail":{"setup":0.7427,"trend":0.6948,"momentum":0.9606,"volume":0.5521}},"fundamental":{"score":0.6735447777310926,"quality":0.9940911764705882,"value":0.1295415357142858,"moat":1.0,"management":0.0},"snapshot":{"rsi14":62.1,"macd_hist":0.00653,"adx14":23.8,"stoch_k":81.1,"atr_pct":0.0322,"sma50_dist":0.0693,"sma200_dist":0.1337,"high_52w_dist":0.0,"low_52w_dist":0.3207,"vol_ratio":0.8,"ret_1m":0.0685,"ret_3m":0.1665,"ret_6m":0.0782,"rel_1m":0.0853,"rel_3m":0.0198},"trade_plan":{"entry":147.31,"stop":137.81,"target1":156.81,"target2":166.31,"rr":1.0,"atr_pct":0.0322,"method":"2x/4x ATR"},"summary":"ABNB surfaced because it lines up on two fronts at once: the chart shows a constructive setup, and the underlying business screens as high quality. The specific triggers were uptrend (above rising 50/200-day mas), holding near 52-week highs, roe 32%, low debt/equity 0.3, and strong margin 20%. That gives it a conviction score of 82/100 \u2014 a research lead to investigate, not a recommendation to buy.","company":{"name":"Airbnb, Inc.","sector":"Consumer Cyclical","industry":"Travel Services","country":"United States","website":"https://www.airbnb.com","employees":8200,"held_institutions":0.88537,"held_insiders":0.01121,"description":"Airbnb, Inc., together with its subsidiaries, operates a platform for stays, experiences, and services worldwide. The company's marketplace connects hosts and guests online or through mobile devices to book spaces, experiences, and services. It also offers gift cards.","holders":[{"name":"Blackrock Inc.","pct":0.0764},{"name":"Vanguard Capital Management LLC","pct":0.0625},{"name":"Harris Associates L.P.","pct":0.045900002},{"name":"State Street Corporation","pct":0.0424},{"name":"Geode Capital Management, LLC","pct":0.0249}],"backing_score":87,"strength_score":82}},{"symbol":"AAPL","market":"US","price":294.3800048828125,"chg_1d":0.0173,"conviction":81,"tier":"both","reasons":["Uptrend (above rising 50/200-day MAs)","Pullback to the 50-day in an uptrend","Oversold bounce in a long-term uptrend","ROE 141%","strong margin 27%"],"technical":{"score":0.7746104915786373,"patterns":["uptrend","pullback_to_trend","oversold_reversal"],"strengths":{"uptrend":1.0,"pullback_to_trend":0.8345,"oversold_reversal":0.7559},"detail":{"setup":1.0,"trend":0.6315,"momentum":0.4763,"volume":0.6749}},"fundamental":{"score":0.651693931932773,"quality":0.9271352941176471,"value":0.15419907142857145,"moat":1.0,"management":0.0},"snapshot":{"rsi14":51.0,"macd_hist":-0.00425,"adx14":24.4,"stoch_k":51.4,"atr_pct":0.0278,"sma50_dist":0.0058,"sma200_dist":0.089,"high_52w_dist":-0.0661,"low_52w_dist":0.4546,"vol_ratio":0.74,"ret_1m":-0.0389,"ret_3m":0.1599,"ret_6m":0.0753,"rel_1m":-0.0221,"rel_3m":0.0132},"trade_plan":{"entry":294.38,"stop":277.98,"target1":310.78,"target2":327.17,"rr":1.0,"atr_pct":0.0278,"method":"2x/4x ATR"},"summary":"AAPL surfaced because it lines up on two fronts at once: the chart shows a constructive setup, and the underlying business screens as high quality. The specific triggers were uptrend (above rising 50/200-day mas), pullback to the 50-day in an uptrend, oversold bounce in a long-term uptrend, roe 141%, and strong margin 27%. That gives it a conviction score of 81/100 \u2014 a research lead to investigate, not a recommendation to buy.","company":{"name":"Apple Inc.","sector":"Technology","industry":"Consumer Electronics","country":"United States","website":"https://www.apple.com","employees":166000,"held_institutions":0.65791,"held_insiders":0.01631,"description":"Apple Inc. designs, manufactures, and markets smartphones, personal computers, tablets, wearables, and accessories worldwide.","holders":[{"name":"Blackrock Inc.","pct":0.0779},{"name":"Vanguard Capital Management LLC","pct":0.064899996},{"name":"State Street Corporation","pct":0.040999997},{"name":"Geode Capital Management, LLC","pct":0.0251},{"name":"Vanguard Portfolio Management LLC","pct":0.0226}],"backing_score":82,"strength_score":79}},{"symbol":"GE","market":"US","price":374.94000244140625,"chg_1d":0.0032,"conviction":81,"tier":"both","reasons":["Uptrend (above rising 50/200-day MAs)","Volume accumulation (OBV rising ahead of price)","Holding near 52-week highs","Bull flag after a sharp advance","Fresh golden cross (50-day over 200-day)","ROE 45%"],"technical":{"score":0.8925435896031001,"patterns":["uptrend","obv_accumulation","high_52w_momentum","bull_flag","golden_cross"],"strengths":{"uptrend":1.0,"golden_cross":0.3333,"bull_flag":0.548,"obv_accumulation":1.0,"high_52w_momentum":0.9893},"detail":{"setup":1.0,"trend":0.9858,"momentum":0.58,"volume":0.7642}},"fundamental":{"score":0.5870994716289594,"quality":0.8460419242647059,"value":0.0,"moat":0.9947308076923078,"management":0.0},"snapshot":{"rsi14":75.0,"macd_hist":0.00446,"adx14":38.9,"stoch_k":90.9,"atr_pct":0.0264,"sma50_dist":0.1824,"sma200_dist":0.2136,"high_52w_dist":0.0,"low_52w_dist":0.5319,"vol_ratio":0.46,"ret_1m":0.1551,"ret_3m":0.3213,"ret_6m":0.2034,"rel_1m":0.1719,"rel_3m":0.1746},"trade_plan":{"entry":374.94,"stop":355.11,"target1":394.77,"target2":441.39,"rr":1.0,"atr_pct":0.0264,"method":"flag pole projection"},"earnings":{"date":"2026-07-16","days":15},"summary":"GE surfaced because it lines up on two fronts at once: the chart shows a constructive setup, and the underlying business screens as high quality. The specific triggers were uptrend (above rising 50/200-day mas), volume accumulation (obv rising ahead of price), holding near 52-week highs, bull flag after a sharp advance, fresh golden cross (50-day over 200-day), and roe 45%. That gives it a conviction score of 81/100 \u2014 a research lead to investigate, not a recommendation to buy.","company":{"name":"GE Aerospace","sector":"Industrials","industry":"Aerospace & Defense","country":"United States","website":"https://www.geaerospace.com","employees":57000,"held_institutions":0.80999,"held_insiders":0.00302,"description":"General Electric Company, doing business as GE Aerospace, designs and produces commercial and defense aircraft engines, integrated engine components, electric power, and aircraft systems. The company operates through two segments, Commercial Engines & Services, and Defense & Propulsion Technologies.","holders":[{"name":"Blackrock Inc.","pct":0.087},{"name":"Vanguard Capital Management LLC","pct":0.0637},{"name":"FMR, LLC","pct":0.0495},{"name":"TCI Fund Management Ltd","pct":0.045500003},{"name":"State Street Corporation","pct":0.0435}],"backing_score":85,"strength_score":72}},{"symbol":"BHP.AX","market":"ASX","price":59.91999816894531,"chg_1d":0.0088,"conviction":80,"tier":"both","reasons":["Uptrend (above rising 50/200-day MAs)","Pullback to the 50-day in an uptrend","ROE 25%","strong margin 19%"],"technical":{"score":0.6381185234755882,"patterns":["uptrend","pullback_to_trend"],"strengths":{"uptrend":1.0,"pullback_to_trend":0.9175},"detail":{"setup":0.9175,"trend":0.5293,"momentum":0.2738,"volume":0.3636}},"fundamental":{"score":0.7706868933193278,"quality":0.9538698404411765,"value":0.6956947857142858,"moat":1.0,"management":0.0},"snapshot":{"rsi14":47.2,"macd_hist":-0.00872,"adx14":16.9,"stoch_k":19.2,"atr_pct":0.0236,"sma50_dist":0.004,"sma200_dist":0.1925,"high_52w_dist":-0.0864,"low_52w_dist":0.5831,"vol_ratio":0.66,"ret_1m":-0.041,"ret_3m":0.1891,"ret_6m":0.3286,"rel_1m":null,"rel_3m":null},"trade_plan":{"entry":59.92,"stop":58.22,"target1":62.75,"target2":65.57,"rr":1.66,"atr_pct":0.0236,"method":"2x/4x ATR"},"summary":"BHP.AX surfaced because it lines up on two fronts at once: the chart shows a constructive setup, and the underlying business screens as high quality. The specific triggers were uptrend (above rising 50/200-day mas), pullback to the 50-day in an uptrend, roe 25%, and strong margin 19%. That gives it a conviction score of 80/100 \u2014 a research lead to investigate, not a recommendation to buy.","company":{"name":"BHP Group Limited","sector":"Basic Materials","industry":"Other Industrial Metals & Mining","country":"Australia","website":"https://www.bhp.com","employees":39369,"held_institutions":0.36047,"held_insiders":0.00034000003,"description":"BHP Group Limited operates as a resources company in Australia, Europe, China, Japan, India, South Korea, rest of Asia, North America, South America, and internationally. The company operates through Copper, Iron Ore, and Coal segments.","holders":[{"name":"Pacer Advisors, Inc.","pct":0.0004},{"name":"Mengis Capital Management, Inc.","pct":0.0},{"name":"Paradigm Asset Management Company, LLC","pct":0.0},{"name":"Wealth Preservation Advisors, LLC","pct":0.0}],"backing_score":44,"strength_score":92}},{"symbol":"MU","market":"US","price":1032.280029296875,"chg_1d":-0.1057,"conviction":76,"tier":"both","reasons":["Uptrend (above rising 50/200-day MAs)","Bull flag after a sharp advance","ROE 67%","low debt/equity 0.1","strong margin 56%"],"technical":{"score":0.5983206735333887,"patterns":["uptrend","bull_flag"],"strengths":{"uptrend":1.0,"bull_flag":0.5481},"detail":{"setup":0.5481,"trend":0.7414,"momentum":0.5211,"volume":0.6044}},"fundamental":{"score":0.7689323571428572,"quality":1.0,"value":0.5946617857142857,"moat":1.0,"management":0.0},"snapshot":{"rsi14":51.8,"macd_hist":-0.01085,"adx14":20.6,"stoch_k":61.2,"atr_pct":0.0926,"sma50_dist":0.2266,"sma200_dist":1.3447,"high_52w_dist":-0.1494,"low_52w_dist":8.8425,"vol_ratio":0.87,"ret_1m":-0.0031,"ret_3m":2.0555,"ret_6m":2.5067,"rel_1m":0.0137,"rel_3m":1.9088},"trade_plan":{"entry":1032.0,"stop":854.35,"target1":1223.0,"target2":1422.0,"rr":1.07,"atr_pct":0.0926,"method":"flag pole projection"},"summary":"MU surfaced because it lines up on two fronts at once: the chart shows a constructive setup, and the underlying business screens as high quality. The specific triggers were uptrend (above rising 50/200-day mas), bull flag after a sharp advance, roe 67%, low debt/equity 0.1, and strong margin 56%. That gives it a conviction score of 76/100 \u2014 a research lead to investigate, not a recommendation to buy.","company":{"name":"Micron Technology, Inc.","sector":"Technology","industry":"Semiconductors","country":"United States","website":"https://www.micron.com","employees":53000,"held_institutions":0.81461996,"held_insiders":0.00253,"description":"Micron Technology, Inc. designs, develops, manufactures, and sells memory and storage products in the United States, Taiwan, Japan, Mainland China, Hong Kong, Europe, and internationally.","holders":[{"name":"Blackrock Inc.","pct":0.0913},{"name":"Vanguard Capital Management LLC","pct":0.0648},{"name":"State Street Corporation","pct":0.0463},{"name":"Capital World Investors","pct":0.0372},{"name":"FMR, LLC","pct":0.028399998}],"backing_score":85,"strength_score":92}},{"symbol":"AXP","market":"US","price":348.0,"chg_1d":0.0288,"conviction":75,"tier":"both","reasons":["Volume accumulation (OBV rising ahead of price)","Double bottom recovering","ROE 34%"],"technical":{"score":0.6944805055263135,"patterns":["obv_accumulation","double_bottom"],"strengths":{"double_bottom":0.6214,"obv_accumulation":1.0},"detail":{"setup":0.7214,"trend":0.3842,"momentum":1.0,"volume":0.7816}},"fundamental":{"score":0.6237580655138979,"quality":0.6485205882352941,"value":0.6532395357142857,"moat":0.9348076923076922,"management":0.0},"snapshot":{"rsi14":69.4,"macd_hist":0.00302,"adx14":24.4,"stoch_k":76.3,"atr_pct":0.0225,"sma50_dist":0.0828,"sma200_dist":0.0295,"high_52w_dist":-0.0958,"low_52w_dist":0.1907,"vol_ratio":0.91,"ret_1m":0.1099,"ret_3m":0.1505,"ret_6m":-0.0728,"rel_1m":0.1267,"rel_3m":0.0038},"trade_plan":{"entry":348.0,"stop":332.34,"target1":363.66,"target2":379.33,"rr":1.0,"atr_pct":0.0225,"method":"2x/4x ATR"},"summary":"AXP surfaced because it lines up on two fronts at once: the chart shows a constructive setup, and the underlying business screens as high quality. The specific triggers were volume accumulation (obv rising ahead of price), double bottom recovering, and roe 34%. That gives it a conviction score of 75/100 \u2014 a research lead to investigate, not a recommendation to buy.","company":{"name":"American Express Company","sector":"Financial Services","industry":"Credit Services","country":"United States","website":"https://www.americanexpress.com","employees":76800,"held_institutions":0.65271,"held_insiders":0.22326,"description":"American Express Company, together with its subsidiaries, operates as an integrated payments company in the United States, Europe, the Middle East and Africa, the Asia Pacific, Australia, New Zealand, Latin America, Canada, the Caribbean, and internationally. It operates through four segments: U.S.","holders":[{"name":"Berkshire Hathaway, Inc","pct":0.22219999},{"name":"Blackrock Inc.","pct":0.0614},{"name":"Vanguard Capital Management LLC","pct":0.0484},{"name":"State Street Corporation","pct":0.0428},{"name":"JPMORGAN CHASE & CO","pct":0.0299}],"backing_score":94,"strength_score":74}},{"symbol":"UNH","market":"US","price":426.5400085449219,"chg_1d":0.0262,"conviction":74,"tier":"technical","reasons":["Uptrend (above rising 50/200-day MAs)","Holding near 52-week highs","Fresh MACD bullish cross","Volume accumulation (OBV rising ahead of price)"],"technical":{"score":0.929405185674784,"patterns":["uptrend","high_52w_momentum","macd_bull_cross","obv_accumulation"],"strengths":{"uptrend":1.0,"obv_accumulation":0.5586,"high_52w_momentum":0.9422,"macd_bull_cross":0.5887},"detail":{"setup":1.0,"trend":0.9059,"momentum":1.0,"volume":0.6077}},"fundamental":{"score":0.3354962284607843,"quality":0.5883955815686275,"value":0.2831899999999999,"moat":0.1739999833333333,"management":0.0},"snapshot":{"rsi14":65.9,"macd_hist":0.00083,"adx14":37.4,"stoch_k":75.1,"atr_pct":0.0242,"sma50_dist":0.0969,"sma200_dist":0.266,"high_52w_dist":-0.0032,"low_52w_dist":0.7939,"vol_ratio":0.68,"ret_1m":0.1229,"ret_3m":0.5763,"ret_6m":0.2967,"rel_1m":0.1397,"rel_3m":0.4296},"trade_plan":{"entry":426.54,"stop":405.86,"target1":447.22,"target2":467.9,"rr":1.0,"atr_pct":0.0242,"method":"2x/4x ATR"},"earnings":{"date":"2026-07-16","days":15},"summary":"UNH surfaced because its price chart triggered our technical signals. The specific triggers were uptrend (above rising 50/200-day mas), holding near 52-week highs, fresh macd bullish cross, and volume accumulation (obv rising ahead of price). That gives it a conviction score of 74/100 \u2014 a research lead to investigate, not a recommendation to buy.","company":{"name":"UnitedHealth Group Incorporated","sector":"Healthcare","industry":"Healthcare Plans","country":"United States","website":"https://www.unitedhealthgroup.com","employees":390000,"held_institutions":0.85801005,"held_insiders":0.00235,"description":"UnitedHealth Group Incorporated operates as a health care company in the United States and internationally. It operates through four segments: Optum Health, Optum Insight, Optum Rx; and UnitedHealthcare.","holders":[{"name":"Blackrock Inc.","pct":0.0809},{"name":"Vanguard Capital Management LLC","pct":0.0648},{"name":"State Street Corporation","pct":0.0499},{"name":"Capital World Investors","pct":0.0306},{"name":"Vanguard Portfolio Management LLC","pct":0.026500002}],"backing_score":85,"strength_score":40}},{"symbol":"GOOGL","market":"US","price":361.2099914550781,"chg_1d":0.0107,"conviction":72,"tier":"both","reasons":["Oversold bounce in a long-term uptrend","Pullback to the 50-day in an uptrend","ROE 39%","low debt/equity 0.2","strong margin 38%"],"technical":{"score":0.5712953276298101,"patterns":["oversold_reversal","pullback_to_trend"],"strengths":{"pullback_to_trend":0.6165,"oversold_reversal":0.7347},"detail":{"setup":0.8888,"trend":0.1797,"momentum":0.4747,"volume":0.3413}},"fundamental":{"score":0.7390625000000001,"quality":1.0,"value":0.4453125,"moat":1.0,"management":0.0},"snapshot":{"rsi14":50.3,"macd_hist":-0.00029,"adx14":18.1,"stoch_k":59.4,"atr_pct":0.032,"sma50_dist":-0.0249,"sma200_dist":0.1445,"high_52w_dist":-0.1029,"low_52w_dist":1.0716,"vol_ratio":0.65,"ret_1m":-0.0403,"ret_3m":0.2561,"ret_6m":0.152,"rel_1m":-0.0235,"rel_3m":0.1094},"trade_plan":{"entry":361.21,"stop":338.07,"target1":384.35,"target2":407.49,"rr":1.0,"atr_pct":0.032,"method":"2x/4x ATR"},"summary":"GOOGL surfaced because it lines up on two fronts at once: the chart shows a constructive setup, and the underlying business screens as high quality. The specific triggers were oversold bounce in a long-term uptrend, pullback to the 50-day in an uptrend, roe 39%, low debt/equity 0.2, and strong margin 38%. That gives it a conviction score of 72/100 \u2014 a research lead to investigate, not a recommendation to buy.","company":{"name":"Alphabet Inc.","sector":"Communication Services","industry":"Internet Content & Information","country":"United States","website":"https://abc.xyz","employees":194668,"held_institutions":0.80671,"held_insiders":0.011729999,"description":"Alphabet Inc. offers various products and platforms in the United States, Europe, the Middle East, Africa, the Asia-Pacific, Canada, and Latin America. It operates through Google Services, Google Cloud, and Other Bets segments.","holders":[{"name":"Blackrock Inc.","pct":0.0767},{"name":"Vanguard Capital Management LLC","pct":0.064899996},{"name":"FMR, LLC","pct":0.040599998},{"name":"State Street Corporation","pct":0.0388},{"name":"Geode Capital Management, LLC","pct":0.026099999}],"backing_score":87,"strength_score":89}},{"symbol":"MA","market":"US","price":522.4400024414062,"chg_1d":0.0172,"conviction":72,"tier":"both","reasons":["Volume accumulation (OBV rising ahead of price)","Double bottom recovering","ROE 232%","strong margin 46%"],"technical":{"score":0.6445312330456338,"patterns":["obv_accumulation","double_bottom"],"strengths":{"double_bottom":0.6194,"obv_accumulation":1.0},"detail":{"setup":0.7194,"trend":0.2307,"momentum":0.9436,"volume":0.7774}},"fundamental":{"score":0.6195083571428572,"quality":0.75,"value":0.3475417857142857,"moat":1.0,"management":0.0},"snapshot":{"rsi14":65.4,"macd_hist":0.00716,"adx14":15.5,"stoch_k":86.7,"atr_pct":0.0226,"sma50_dist":0.0514,"sma200_dist":-0.0168,"high_52w_dist":-0.1278,"low_52w_dist":0.1079,"vol_ratio":0.58,"ret_1m":0.0549,"ret_3m":0.0456,"ret_6m":-0.096,"rel_1m":0.0717,"rel_3m":-0.1011},"trade_plan":{"entry":522.44,"stop":498.86,"target1":546.02,"target2":569.59,"rr":1.0,"atr_pct":0.0226,"method":"2x/4x ATR"},"summary":"MA surfaced because it lines up on two fronts at once: the chart shows a constructive setup, and the underlying business screens as high quality. The specific triggers were volume accumulation (obv rising ahead of price), double bottom recovering, roe 232%, and strong margin 46%. That gives it a conviction score of 72/100 \u2014 a research lead to investigate, not a recommendation to buy.","company":{"name":"Mastercard Incorporated","sector":"Financial Services","industry":"Credit Services","country":"United States","website":"https://www.mastercard.com","employees":39800,"held_institutions":0.91480005,"held_insiders":0.00114,"description":"Mastercard Incorporated, a technology company, provides transaction processing and other payment-related products and services in the United States and internationally.","holders":[{"name":"Blackrock Inc.","pct":0.0764},{"name":"Mastercard Foundation Asset Management Corp","pct":0.0744},{"name":"Vanguard Capital Management LLC","pct":0.059699997},{"name":"State Street Corporation","pct":0.0416},{"name":"JPMORGAN CHASE & CO","pct":0.0372}],"backing_score":85,"strength_score":74}},{"symbol":"LLY","market":"US","price":1191.739990234375,"chg_1d":-0.0064,"conviction":72,"tier":"both","reasons":["Uptrend (above rising 50/200-day MAs)","Holding near 52-week highs","ROE 107%","strong margin 35%"],"technical":{"score":0.7207951735673738,"patterns":["uptrend","high_52w_momentum"],"strengths":{"uptrend":1.0,"high_52w_momentum":0.6059},"detail":{"setup":0.6059,"trend":0.8735,"momentum":0.86,"volume":0.6248}},"fundamental":{"score":0.5858735294117647,"quality":0.8396838235294117,"value":0.0,"moat":1.0,"management":0.0},"snapshot":{"rsi14":64.5,"macd_hist":0.00327,"adx14":31.6,"stoch_k":80.5,"atr_pct":0.0322,"sma50_dist":0.1364,"sma200_dist":0.2127,"high_52w_dist":-0.0311,"low_52w_dist":0.9048,"vol_ratio":0.76,"ret_1m":0.1012,"ret_3m":0.2957,"ret_6m":0.1048,"rel_1m":0.118,"rel_3m":0.149},"trade_plan":{"entry":1192.0,"stop":1115.0,"target1":1268.0,"target2":1345.0,"rr":1.0,"atr_pct":0.0322,"method":"2x/4x ATR"},"summary":"LLY surfaced because it lines up on two fronts at once: the chart shows a constructive setup, and the underlying business screens as high quality. The specific triggers were uptrend (above rising 50/200-day mas), holding near 52-week highs, roe 107%, and strong margin 35%. That gives it a conviction score of 72/100 \u2014 a research lead to investigate, not a recommendation to buy.","company":{"name":"Eli Lilly and Company","sector":"Healthcare","industry":"Drug Manufacturers - General","country":"United States","website":"https://www.lilly.com","employees":50000,"held_institutions":0.85322,"held_insiders":0.00155,"description":"Eli Lilly and Company discovers, develops, manufactures, and markets human pharmaceutical products in the United States, Europe, China, Japan, and internationally.","holders":[{"name":"Lilly Endowment, Inc","pct":0.097600006},{"name":"Blackrock Inc.","pct":0.0705},{"name":"Vanguard Capital Management LLC","pct":0.056700002},{"name":"PNC Financial Services Group, Inc.","pct":0.0545},{"name":"State Street Corporation","pct":0.0378}],"backing_score":85,"strength_score":72}},{"symbol":"PANW","market":"US","price":352.0400085449219,"chg_1d":0.0323,"conviction":71,"tier":"technical","reasons":["Uptrend (above rising 50/200-day MAs)","Holding near 52-week highs","Fresh MACD bullish cross","low debt/equity 0.1"],"technical":{"score":0.8936969442775878,"patterns":["uptrend","high_52w_momentum","macd_bull_cross"],"strengths":{"uptrend":1.0,"high_52w_momentum":1.0,"macd_bull_cross":0.5},"detail":{"setup":1.0,"trend":1.0,"momentum":0.72,"volume":0.5341}},"fundamental":{"score":0.26807153846153847,"quality":0.5993375,"value":0.0,"moat":0.11334615384615383,"management":0.0},"snapshot":{"rsi14":81.4,"macd_hist":0.01311,"adx14":45.8,"stoch_k":97.1,"atr_pct":0.0385,"sma50_dist":0.4196,"sma200_dist":0.7537,"high_52w_dist":0.0,"low_52w_dist":1.4849,"vol_ratio":0.83,"ret_1m":0.1716,"ret_3m":1.1959,"ret_6m":0.8841,"rel_1m":0.1884,"rel_3m":1.0492},"trade_plan":{"entry":352.04,"stop":324.91,"target1":379.17,"target2":406.3,"rr":1.0,"atr_pct":0.0385,"method":"2x/4x ATR"},"summary":"PANW surfaced because its price chart triggered our technical signals. The specific triggers were uptrend (above rising 50/200-day mas), holding near 52-week highs, fresh macd bullish cross, and low debt/equity 0.1. That gives it a conviction score of 71/100 \u2014 a research lead to investigate, not a recommendation to buy.","company":{"name":"Palo Alto Networks, Inc.","sector":"Technology","industry":"Software - Infrastructure","country":"United States","website":"https://www.paloaltonetworks.com","employees":21491,"held_institutions":0.83115,"held_insiders":0.00759,"description":"Palo Alto Networks, Inc. provides cybersecurity solutions in the Americas, Europe, the Middle East, Africa, the Asia Pacific, and Japan.","holders":[{"name":"Blackrock Inc.","pct":0.7436},{"name":"Vanguard Capital Management LLC","pct":0.5417},{"name":"State Street Corporation","pct":0.3643},{"name":"Morgan Stanley","pct":0.3318},{"name":"Bank of America Corporation","pct":0.2308}],"backing_score":86,"strength_score":33}},{"symbol":"JNJ","market":"US","price":253.97999572753906,"chg_1d":0.0,"conviction":71,"tier":"both","reasons":["Uptrend (above rising 50/200-day MAs)","Holding near 52-week highs","ROE 26%","strong margin 22%"],"technical":{"score":0.5869903138815005,"patterns":["uptrend","high_52w_momentum"],"strengths":{"uptrend":1.0,"high_52w_momentum":0.4157},"detail":{"setup":0.4157,"trend":0.7308,"momentum":0.86,"volume":0.5203}},"fundamental":{"score":0.7033066323529412,"quality":0.944514705882353,"value":0.3775037500000001,"moat":1.0,"management":0.0},"snapshot":{"rsi14":67.4,"macd_hist":0.00864,"adx14":24.4,"stoch_k":87.7,"atr_pct":0.0216,"sma50_dist":0.0948,"sma200_dist":0.1623,"high_52w_dist":-0.0175,"low_52w_dist":0.6368,"vol_ratio":0.72,"ret_1m":0.1363,"ret_3m":0.039,"ret_6m":0.2236,"rel_1m":0.1531,"rel_3m":-0.1077},"trade_plan":{"entry":253.98,"stop":243.03,"target1":264.93,"target2":275.88,"rr":1.0,"atr_pct":0.0216,"method":"2x/4x ATR"},"earnings":{"date":"2026-07-15","days":14},"summary":"JNJ surfaced because it lines up on two fronts at once: the chart shows a constructive setup, and the underlying business screens as high quality. The specific triggers were uptrend (above rising 50/200-day mas), holding near 52-week highs, roe 26%, and strong margin 22%. That gives it a conviction score of 71/100 \u2014 a research lead to investigate, not a recommendation to buy.","company":{"name":"Johnson & Johnson","sector":"Healthcare","industry":"Drug Manufacturers - General","country":"United States","website":"https://www.jnj.com","employees":138200,"held_institutions":0.76832,"held_insiders":0.00046999997,"description":"Johnson & Johnson, together with its subsidiaries, engages in the research and development, manufacture, and sale of a range of products in the healthcare field worldwide. It operates in two segments, Innovative Medicine and MedTech.","holders":[{"name":"Blackrock Inc.","pct":0.088599995},{"name":"Vanguard Capital Management LLC","pct":0.0651},{"name":"State Street Corporation","pct":0.0554},{"name":"Vanguard Portfolio Management LLC","pct":0.026400002},{"name":"JPMORGAN CHASE & CO","pct":0.026199998}],"backing_score":85,"strength_score":85}},{"symbol":"AMZN","market":"US","price":241.6999969482422,"chg_1d":0.0141,"conviction":70,"tier":"both","reasons":["Fresh MACD bullish cross","Oversold bounce in a long-term uptrend","Pullback to the 50-day in an uptrend","ROE 24%"],"technical":{"score":0.6514076917435337,"patterns":["macd_bull_cross","oversold_reversal","pullback_to_trend"],"strengths":{"pullback_to_trend":0.3544,"macd_bull_cross":1.0,"oversold_reversal":0.7119},"detail":{"setup":0.9005,"trend":0.2853,"momentum":0.5814,"volume":0.5851}},"fundamental":{"score":0.5983165846800259,"quality":0.8685352941176471,"value":0.28220464285714286,"moat":0.7778461538461539,"management":0.0},"snapshot":{"rsi14":47.8,"macd_hist":0.00195,"adx14":28.4,"stoch_k":59.5,"atr_pct":0.0348,"sma50_dist":-0.0542,"sma200_dist":0.0377,"high_52w_dist":-0.1211,"low_52w_dist":0.2159,"vol_ratio":0.84,"ret_1m":-0.0749,"ret_3m":0.1605,"ret_6m":0.0415,"rel_1m":-0.0581,"rel_3m":0.0138},"trade_plan":{"entry":241.7,"stop":225.55,"target1":258.52,"target2":275.35,"rr":1.04,"atr_pct":0.0348,"method":"2x/4x ATR"},"summary":"AMZN surfaced because it lines up on two fronts at once: the chart shows a constructive setup, and the underlying business screens as high quality. The specific triggers were fresh macd bullish cross, oversold bounce in a long-term uptrend, pullback to the 50-day in an uptrend, and roe 24%. That gives it a conviction score of 70/100 \u2014 a research lead to investigate, not a recommendation to buy.","company":{"name":"Amazon.com, Inc.","sector":"Consumer Cyclical","industry":"Internet Retail","country":"United States","website":"https://www.amazon.com","employees":1575000,"held_institutions":0.67974997,"held_insiders":0.08898,"description":"Amazon.com, Inc. engages in the retail sale of consumer products, advertising, and subscriptions service through online and physical stores in North America and internationally. The company operates through three segments: North America, International, and Amazon Web Services (AWS).","holders":[{"name":"Blackrock Inc.","pct":0.0684},{"name":"Vanguard Capital Management LLC","pct":0.0587},{"name":"State Street Corporation","pct":0.0363},{"name":"FMR, LLC","pct":0.033299997},{"name":"Geode Capital Management, LLC","pct":0.0217}],"backing_score":96,"strength_score":72}},{"symbol":"TXN","market":"US","price":298.4100036621094,"chg_1d":0.0011,"conviction":70,"tier":"both","reasons":["Uptrend (above rising 50/200-day MAs)","Pullback to the 50-day in an uptrend","ROE 32%","strong margin 29%"],"technical":{"score":0.6140670040180318,"patterns":["uptrend","pullback_to_trend"],"strengths":{"uptrend":1.0,"pullback_to_trend":0.7677},"detail":{"setup":0.7677,"trend":0.5722,"momentum":0.3472,"volume":0.5254}},"fundamental":{"score":0.6183876470588235,"quality":0.9209691176470588,"value":0.0,"moat":1.0,"management":0.0},"snapshot":{"rsi14":49.9,"macd_hist":-0.00871,"adx14":19.3,"stoch_k":32.1,"atr_pct":0.05,"sma50_dist":0.0128,"sma200_dist":0.3884,"high_52w_dist":-0.1019,"low_52w_dist":0.9462,"vol_ratio":0.8,"ret_1m":0.0178,"ret_3m":0.5371,"ret_6m":0.6985,"rel_1m":0.0346,"rel_3m":0.3904},"trade_plan":{"entry":298.41,"stop":273.88,"target1":328.25,"target2":358.08,"rr":1.22,"atr_pct":0.05,"method":"2x/4x ATR"},"earnings":{"date":"2026-07-22","days":21},"summary":"TXN surfaced because it lines up on two fronts at once: the chart shows a constructive setup, and the underlying business screens as high quality. The specific triggers were uptrend (above rising 50/200-day mas), pullback to the 50-day in an uptrend, roe 32%, and strong margin 29%. That gives it a conviction score of 70/100 \u2014 a research lead to investigate, not a recommendation to buy.","company":{"name":"Texas Instruments Incorporated","sector":"Technology","industry":"Semiconductors","country":"United States","website":"https://www.ti.com","employees":33000,"held_institutions":0.92603993,"held_insiders":0.00279,"description":"Texas Instruments Incorporated designs, manufactures, and sells semiconductors to electronics designers and manufacturers in the United States, China, the rest of Asia, Europe, the Middle East, Africa, Japan, and internationally. It operates through Analog and Embedded Processing segments.","holders":[{"name":"Blackrock Inc.","pct":0.0896},{"name":"Vanguard Capital Management LLC","pct":0.0648},{"name":"State Street Corporation","pct":0.0473},{"name":"JPMORGAN CHASE & CO","pct":0.0422},{"name":"Vanguard Portfolio Management LLC","pct":0.031400003}],"backing_score":85,"strength_score":76}},{"symbol":"ADBE","market":"US","price":210.97999572753906,"chg_1d":0.0291,"conviction":66,"tier":"fundamental","reasons":["Fresh MACD bullish cross","ROE 63%","strong margin 29%","reasonable P/E 12"],"technical":{"score":0.1937631467220349,"patterns":["macd_bull_cross"],"strengths":{"macd_bull_cross":1.0},"detail":{"setup":0.1,"trend":0.1648,"momentum":0.55,"volume":0.0713}},"fundamental":{"score":0.8310548819327731,"quality":0.9537602941176471,"value":0.9977538214285714,"moat":1.0,"management":0.0},"snapshot":{"rsi14":44.2,"macd_hist":0.00435,"adx14":23.5,"stoch_k":36.5,"atr_pct":0.0435,"sma50_dist":-0.104,"sma200_dist":-0.2708,"high_52w_dist":-0.448,"low_52w_dist":0.0908,"vol_ratio":0.67,"ret_1m":-0.2301,"ret_3m":-0.1321,"ret_6m":-0.4026,"rel_1m":-0.2133,"rel_3m":-0.2788},"trade_plan":{"entry":210.98,"stop":192.63,"target1":229.33,"target2":247.69,"rr":1.0,"atr_pct":0.0435,"method":"2x/4x ATR"},"summary":"ADBE surfaced because the underlying business screens as high quality and reasonably valued, even though the chart isn't flashing a setup yet. The specific triggers were fresh macd bullish cross, roe 63%, strong margin 29%, and reasonable p/e 12. That gives it a conviction score of 66/100 \u2014 a research lead to investigate, not a recommendation to buy.","company":{"name":"Adobe Inc.","sector":"Technology","industry":"Software - Application","country":"United States","website":"https://www.adobe.com","employees":31360,"held_institutions":0.88064003,"held_insiders":0.00232,"description":"Adobe Inc. operates as a technology company worldwide. The Digital Media segment offers products and services that enable individuals, teams, and enterprises to create, publish, and promote content.","holders":[{"name":"Blackrock Inc.","pct":0.1027},{"name":"Vanguard Capital Management LLC","pct":0.0671},{"name":"State Street Corporation","pct":0.050100002},{"name":"Geode Capital Management, LLC","pct":0.0295},{"name":"Vanguard Portfolio Management LLC","pct":0.0251}],"backing_score":85,"strength_score":98}},{"symbol":"FMG.AX","market":"ASX","price":19.239999771118164,"chg_1d":0.0047,"conviction":66,"tier":"fundamental","reasons":["low debt/equity 0.3","strong margin 23%","reasonable P/E 11"],"technical":{"score":0.0,"patterns":[],"strengths":{},"detail":{"setup":0.0,"trend":0.1895,"momentum":0.0,"volume":0.0969}},"fundamental":{"score":0.8276549829166666,"quality":0.9781999833333332,"value":1.0,"moat":0.9454999583333333,"management":0.0},"snapshot":{"rsi14":38.7,"macd_hist":-0.00298,"adx14":22.8,"stoch_k":21.3,"atr_pct":0.0272,"sma50_dist":-0.0732,"sma200_dist":-0.073,"high_52w_dist":-0.1631,"low_52w_dist":0.1877,"vol_ratio":0.64,"ret_1m":-0.1453,"ret_3m":-0.0527,"ret_6m":-0.1274,"rel_1m":null,"rel_3m":null},"trade_plan":{"entry":19.24,"stop":18.72,"target1":20.29,"target2":21.33,"rr":2.0,"atr_pct":0.0272,"method":"2x/4x ATR"},"summary":"FMG.AX surfaced because the underlying business screens as high quality and reasonably valued, even though the chart isn't flashing a setup yet. The specific triggers were low debt/equity 0.3, strong margin 23%, and reasonable p/e 11. That gives it a conviction score of 66/100 \u2014 a research lead to investigate, not a recommendation to buy.","company":{"name":"Fortescue Ltd","sector":"Basic Materials","industry":"Other Industrial Metals & Mining","country":"Australia","website":"https://www.fortescue.com","employees":15745,"held_institutions":0.22142,"held_insiders":0.48714,"description":"Fortescue Ltd engages in the exploration, development, production, processing, and sale of iron ore in Australia, China, and internationally. The company explores for copper and lithium deposits; and rare earth elements.","holders":[{"name":"Pacer Advisors, Inc.","pct":0.0011},{"name":"Ancora Advisors, LLC","pct":0.0}],"backing_score":42,"strength_score":97}},{"symbol":"COL.AX","market":"ASX","price":23.350000381469727,"chg_1d":-0.0419,"conviction":65,"tier":"technical","reasons":["Uptrend (above rising 50/200-day MAs)","Volume accumulation (OBV rising ahead of price)","Double bottom recovering","ROE 27%"],"technical":{"score":0.81394504325863,"patterns":["uptrend","obv_accumulation","double_bottom"],"strengths":{"uptrend":1.0,"double_bottom":0.7969,"obv_accumulation":0.8551},"detail":{"setup":0.9659,"trend":0.7601,"momentum":0.6194,"volume":0.648}},"fundamental":{"score":0.4025094,"quality":0.528125,"value":0.33129700000000006,"moat":0.5,"management":0.0},"snapshot":{"rsi14":52.0,"macd_hist":-0.00034,"adx14":31.2,"stoch_k":72.0,"atr_pct":0.0231,"sma50_dist":0.0393,"sma200_dist":0.0539,"high_52w_dist":-0.0434,"low_52w_dist":0.1548,"vol_ratio":1.77,"ret_1m":0.0755,"ret_3m":0.0633,"ret_6m":0.0881,"rel_1m":null,"rel_3m":null},"trade_plan":{"entry":23.35,"stop":22.27,"target1":24.43,"target2":25.51,"rr":1.0,"atr_pct":0.0231,"method":"2x/4x ATR"},"summary":"COL.AX surfaced because its price chart triggered our technical signals. The specific triggers were uptrend (above rising 50/200-day mas), volume accumulation (obv rising ahead of price), double bottom recovering, and roe 27%. That gives it a conviction score of 65/100 \u2014 a research lead to investigate, not a recommendation to buy.","company":{"name":"Coles Group Limited","sector":"Consumer Defensive","industry":"Grocery Stores","country":"Australia","website":"https://www.colesgroup.com.au","employees":115000,"held_institutions":0.4112,"held_insiders":0.00564,"description":"Coles Group Limited operates as a retailer in Australia. It operates through Supermarkets and Liquor segments. The company operates various supermarkets, which offers fresh food, groceries, general merchandise, and liquor; and coles.com.au, which offers a choice of home delivery, including same-day, overnight drop and\u2026","holders":[{"name":"Pacer Advisors, Inc.","pct":0.0004}],"backing_score":51,"strength_score":48}}],"radar":[{"symbol":"MSFT","market":"US","price":384.2799987792969,"chg_1d":0.0302,"conviction":62,"tier":"fundamental","patterns":[],"snapshot":{"rsi14":46.9,"adx14":23.4,"high_52w_dist":-0.2911,"ret_1m":-0.1656,"ret_3m":0.0381,"rel_1m":-0.1488,"rel_3m":-0.1086}},{"symbol":"META","market":"US","price":612.9099731445312,"chg_1d":0.0881,"conviction":62,"tier":"fundamental","patterns":["macd_bull_cross"],"snapshot":{"rsi14":58.5,"adx14":18.8,"high_52w_dist":-0.2242,"ret_1m":0.0207,"ret_3m":0.0713,"rel_1m":0.0375,"rel_3m":-0.0754}},{"symbol":"QCOM","market":"US","price":181.9199981689453,"chg_1d":-0.0155,"conviction":62,"tier":"fundamental","patterns":[],"snapshot":{"rsi14":40.0,"adx14":15.7,"high_52w_dist":-0.2753,"ret_1m":-0.2056,"ret_3m":0.4126,"rel_1m":-0.1888,"rel_3m":0.2659}},{"symbol":"MCD","market":"US","price":269.42999267578125,"chg_1d":-0.0033,"conviction":62,"tier":"fundamental","patterns":[],"snapshot":{"rsi14":41.0,"adx14":21.5,"high_52w_dist":-0.21,"ret_1m":-0.0242,"ret_3m":-0.1331,"rel_1m":-0.0074,"rel_3m":-0.2798}},{"symbol":"V","market":"US","price":351.0799865722656,"chg_1d":0.0233,"conviction":61,"tier":"both","patterns":["high_52w_momentum"],"snapshot":{"rsi14":71.5,"adx14":20.5,"high_52w_dist":-0.0217,"ret_1m":0.0877,"ret_3m":0.1616,"rel_1m":0.1045,"rel_3m":0.0149}},{"symbol":"REGN","market":"US","price":624.719970703125,"chg_1d":0.0019,"conviction":61,"tier":"both","patterns":["obv_accumulation","bollinger_squeeze"],"snapshot":{"rsi14":46.5,"adx14":30.0,"high_52w_dist":-0.2309,"ret_1m":0.0401,"ret_3m":-0.1914,"rel_1m":0.0569,"rel_3m":-0.3381}},{"symbol":"AMAT","market":"US","price":650.9099731445312,"chg_1d":-0.0997,"conviction":60,"tier":"both","patterns":["uptrend"],"snapshot":{"rsi14":60.4,"adx14":34.6,"high_52w_dist":-0.0997,"ret_1m":0.4207,"ret_3m":0.9044,"rel_1m":0.4375,"rel_3m":0.7577}},{"symbol":"NFLX","market":"US","price":74.19000244140625,"chg_1d":0.0391,"conviction":60,"tier":"fundamental","patterns":[],"snapshot":{"rsi14":37.5,"adx14":39.6,"high_52w_dist":-0.4281,"ret_1m":-0.1358,"ret_3m":-0.2284,"rel_1m":-0.119,"rel_3m":-0.3751}},{"symbol":"UBER","market":"US","price":72.66000366210938,"chg_1d":0.0069,"conviction":60,"tier":"fundamental","patterns":["obv_accumulation"],"snapshot":{"rsi14":50.4,"adx14":13.2,"high_52w_dist":-0.2741,"ret_1m":-0.015,"ret_3m":0.0101,"rel_1m":0.0018,"rel_3m":-0.1366}},{"symbol":"PG","market":"US","price":147.42999267578125,"chg_1d":0.0054,"conviction":60,"tier":"fundamental","patterns":[],"snapshot":{"rsi14":49.7,"adx14":17.2,"high_52w_dist":-0.1182,"ret_1m":0.051,"ret_3m":0.0207,"rel_1m":0.0678,"rel_3m":-0.126}},{"symbol":"ALL.AX","market":"ASX","price":59.97999954223633,"chg_1d":-0.0211,"conviction":60,"tier":"fundamental","patterns":["obv_accumulation"],"snapshot":{"rsi14":71.3,"adx14":29.1,"high_52w_dist":-0.177,"ret_1m":0.1934,"ret_3m":0.3232,"rel_1m":null,"rel_3m":null}},{"symbol":"NVDA","market":"US","price":197.5800018310547,"chg_1d":-0.0125,"conviction":58,"tier":"fundamental","patterns":[],"snapshot":{"rsi14":43.3,"adx14":17.6,"high_52w_dist":-0.1619,"ret_1m":-0.1194,"ret_3m":0.1329,"rel_1m":-0.1026,"rel_3m":-0.0138}},{"symbol":"WOW.AX","market":"ASX","price":39.310001373291016,"chg_1d":-0.018,"conviction":58,"tier":"technical","patterns":["uptrend","obv_accumulation","high_52w_momentum"],"snapshot":{"rsi14":63.9,"adx14":40.8,"high_52w_dist":-0.0306,"ret_1m":0.1212,"ret_3m":0.0796,"rel_1m":null,"rel_3m":null}},{"symbol":"SBUX","market":"US","price":103.38999938964844,"chg_1d":0.0117,"conviction":57,"tier":"technical","patterns":["uptrend","obv_accumulation","pullback_to_trend"],"snapshot":{"rsi14":55.9,"adx14":15.6,"high_52w_dist":-0.0321,"ret_1m":0.0713,"ret_3m":0.154,"rel_1m":0.0881,"rel_3m":0.0073}},{"symbol":"RIO.AX","market":"ASX","price":170.80999755859375,"chg_1d":-0.0099,"conviction":57,"tier":"fundamental","patterns":[],"snapshot":{"rsi14":38.2,"adx14":20.2,"high_52w_dist":-0.1217,"ret_1m":-0.0939,"ret_3m":0.0581,"rel_1m":null,"rel_3m":null}},{"symbol":"LRCX","market":"US","price":391.260009765625,"chg_1d":-0.0971,"conviction":56,"tier":"both","patterns":["uptrend"],"snapshot":{"rsi14":56.3,"adx14":28.8,"high_52w_dist":-0.0971,"ret_1m":0.2338,"ret_3m":0.8312,"rel_1m":0.2506,"rel_3m":0.6845}},{"symbol":"KO","market":"US","price":81.29000091552734,"chg_1d":0.0002,"conviction":56,"tier":"fundamental","patterns":["uptrend","macd_bull_cross"],"snapshot":{"rsi14":53.6,"adx14":14.0,"high_52w_dist":-0.0275,"ret_1m":0.0337,"ret_3m":0.0689,"rel_1m":0.0505,"rel_3m":-0.0778}},{"symbol":"WES.AX","market":"ASX","price":90.5,"chg_1d":0.0011,"conviction":56,"tier":"technical","patterns":["obv_accumulation","high_52w_momentum","bull_flag"],"snapshot":{"rsi14":83.0,"adx14":44.3,"high_52w_dist":-0.045,"ret_1m":0.1348,"ret_3m":0.2413,"rel_1m":null,"rel_3m":null}},{"symbol":"REA.AX","market":"ASX","price":139.1699981689453,"chg_1d":-0.0001,"conviction":56,"tier":"fundamental","patterns":[],"snapshot":{"rsi14":39.6,"adx14":31.7,"high_52w_dist":-0.4712,"ret_1m":-0.0798,"ret_3m":-0.1103,"rel_1m":null,"rel_3m":null}},{"symbol":"CRM","market":"US","price":163.22999572753906,"chg_1d":0.0419,"conviction":55,"tier":"fundamental","patterns":["macd_bull_cross"],"snapshot":{"rsi14":47.1,"adx14":19.1,"high_52w_dist":-0.4035,"ret_1m":-0.2212,"ret_3m":-0.1256,"rel_1m":-0.2044,"rel_3m":-0.2723}},{"symbol":"BRK-B","market":"US","price":499.739990234375,"chg_1d":-0.0013,"conviction":55,"tier":"fundamental","patterns":[],"snapshot":{"rsi14":61.4,"adx14":20.4,"high_52w_dist":-0.0274,"ret_1m":0.0626,"ret_3m":0.0429,"rel_1m":0.0794,"rel_3m":-0.1038}},{"symbol":"ABBV","market":"US","price":251.05999755859375,"chg_1d":-0.0023,"conviction":55,"tier":"technical","patterns":["obv_accumulation","high_52w_momentum"],"snapshot":{"rsi14":72.2,"adx14":27.8,"high_52w_dist":-0.0128,"ret_1m":0.1791,"ret_3m":0.1544,"rel_1m":0.1959,"rel_3m":0.0077}},{"symbol":"MRK","market":"US","price":125.37000274658203,"chg_1d":-0.0244,"conviction":55,"tier":"both","patterns":["uptrend"],"snapshot":{"rsi14":60.1,"adx14":20.4,"high_52w_dist":-0.031,"ret_1m":0.0886,"ret_3m":0.0422,"rel_1m":0.1054,"rel_3m":-0.1045}},{"symbol":"PME.AX","market":"ASX","price":202.8699951171875,"chg_1d":-0.0028,"conviction":54,"tier":"fundamental","patterns":["obv_accumulation"],"snapshot":{"rsi14":86.6,"adx14":53.9,"high_52w_dist":-0.3861,"ret_1m":0.4043,"ret_3m":0.7354,"rel_1m":null,"rel_3m":null}},{"symbol":"PLTR","market":"US","price":125.7300033569336,"chg_1d":0.0777,"conviction":52,"tier":"fundamental","patterns":[],"snapshot":{"rsi14":48.4,"adx14":21.7,"high_52w_dist":-0.3931,"ret_1m":-0.2174,"ret_3m":-0.1405,"rel_1m":-0.2006,"rel_3m":-0.2872}},{"symbol":"CSCO","market":"US","price":117.01000213623047,"chg_1d":-0.0038,"conviction":51,"tier":"fundamental","patterns":["uptrend"],"snapshot":{"rsi14":50.2,"adx14":24.9,"high_52w_dist":-0.0999,"ret_1m":-0.0356,"ret_3m":0.5081,"rel_1m":-0.0188,"rel_3m":0.3614}},{"symbol":"SPGI","market":"US","price":414.9700012207031,"chg_1d":0.0189,"conviction":51,"tier":"fundamental","patterns":["obv_accumulation"],"snapshot":{"rsi14":50.5,"adx14":8.8,"high_52w_dist":-0.2644,"ret_1m":-0.0317,"ret_3m":-0.0244,"rel_1m":-0.0149,"rel_3m":-0.1711}},{"symbol":"LIN","market":"US","price":533.5499877929688,"chg_1d":0.0282,"conviction":51,"tier":"fundamental","patterns":["uptrend","macd_bull_cross"],"snapshot":{"rsi14":62.9,"adx14":13.1,"high_52w_dist":0.0,"ret_1m":0.0727,"ret_3m":0.0762,"rel_1m":0.0895,"rel_3m":-0.0705}},{"symbol":"AVGO","market":"US","price":369.3399963378906,"chg_1d":-0.0223,"conviction":50,"tier":"fundamental","patterns":[],"snapshot":{"rsi14":42.0,"adx14":20.8,"high_52w_dist":-0.2331,"ret_1m":-0.197,"ret_3m":0.1933,"rel_1m":-0.1802,"rel_3m":0.0466}},{"symbol":"BLK","market":"US","price":980.3800048828125,"chg_1d":0.0196,"conviction":50,"tier":"fundamental","patterns":[],"snapshot":{"rsi14":41.1,"adx14":20.0,"high_52w_dist":-0.1848,"ret_1m":-0.0395,"ret_3m":0.0194,"rel_1m":-0.0227,"rel_3m":-0.1273}}],"movers":{"gainers":[{"symbol":"META","market":"US","price":612.9099731445312,"chg_1d":0.0881},{"symbol":"ADA-USD","market":"Crypto","price":0.15559999644756317,"chg_1d":0.0793},{"symbol":"PLTR","market":"US","price":125.7300033569336,"chg_1d":0.0777},{"symbol":"MSTR","market":"US","price":93.38999938964844,"chg_1d":0.0743},{"symbol":"NOW","market":"US","price":105.80000305175781,"chg_1d":0.0657}],"losers":[{"symbol":"MU","market":"US","price":1032.280029296875,"chg_1d":-0.1057},{"symbol":"AMAT","market":"US","price":650.9099731445312,"chg_1d":-0.0997},{"symbol":"LRCX","market":"US","price":391.260009765625,"chg_1d":-0.0971},{"symbol":"INTC","market":"US","price":127.0199966430664,"chg_1d":-0.0903},{"symbol":"CAT","market":"US","price":991.4099731445312,"chg_1d":-0.069}]}}